spuco/__init__.py
spuco/datasets/__init__.py
spuco/datasets/base_spuco_compatible_dataset.py
spuco/datasets/base_spuco_dataset.py
spuco/datasets/bffhq.py
spuco/datasets/group_labeled_dataset_wrapper.py
spuco/datasets/index_dataset_wrapper.py
spuco/datasets/spuco_animals.py
spuco/datasets/spuco_birds.py
spuco/datasets/spuco_dogs.py
spuco/datasets/spuco_image_folder.py
spuco/datasets/spuco_mnist.py
spuco/datasets/spuco_mnist_config.py
spuco/datasets/spuco_sun.py
spuco/datasets/spurious_target_dataset_wrapper.py
spuco/datasets/urban_cars.py
spuco/datasets/wilds_dataset_wrapper.py
spuco/end2end/__init__.py
spuco/end2end/lff.py
spuco/evaluate/__init__.py
spuco/evaluate/evaluator.py
spuco/evaluate/gradcam_evaluator.py
spuco/evaluate/group_evaluator.py
spuco/group_inference/__init__.py
spuco/group_inference/base_group_inference.py
spuco/group_inference/cluster.py
spuco/group_inference/cnc_inference.py
spuco/group_inference/eiil.py
spuco/group_inference/george_inference.py
spuco/group_inference/jtt_inference.py
spuco/group_inference/spare_inference.py
spuco/group_inference/ssa.py
spuco/group_inference/george_utils/__init__.py
spuco/group_inference/george_utils/cluster.py
spuco/group_inference/george_utils/fast_sil.py
spuco/group_inference/george_utils/utils.py
spuco/last_layer_retrain/__init__.py
spuco/last_layer_retrain/dfr.py
spuco/last_layer_retrain/dispel.py
spuco/models/__init__.py
spuco/models/bert.py
spuco/models/distilbert.py
spuco/models/lenet.py
spuco/models/mlp.py
spuco/models/model_factory.py
spuco/models/spuco_model.py
spuco/robust_train/__init__.py
spuco/robust_train/base_robust_train.py
spuco/robust_train/class_balance_batch_erm.py
spuco/robust_train/cnc_train.py
spuco/robust_train/custom_sample_erm.py
spuco/robust_train/downsample_erm.py
spuco/robust_train/erm.py
spuco/robust_train/group_balance_batch_erm.py
spuco/robust_train/group_dro.py
spuco/robust_train/pde.py
spuco/robust_train/pgi.py
spuco/robust_train/spare_train.py
spuco-2.0.3.dist-info/LICENSE.txt
spuco-2.0.3.dist-info/METADATA
spuco-2.0.3.dist-info/WHEEL
spuco-2.0.3.dist-info/top_level.txt
spuco-2.0.3.dist-info/RECORD
