Metadata-Version: 2.1
Name: spuco
Version: 2.0.3
Summary: SpuCo: Spurious Correlations Datasets and Benchmarks
Home-page: https://github.com/BigML-CS-UCLA/SpuCo
Author: Siddharth Joshi
Author-email: Siddharth Joshi <sjoshi804@cs.ucla.edu>
Project-URL: Source, https://github.com/BigML-CS-UCLA/SpuCo
Classifier: Development Status :: 5 - Production/Stable
Classifier: Programming Language :: Python :: 3
Classifier: Programming Language :: Python :: 3.10
Classifier: Topic :: Scientific/Engineering
Classifier: Topic :: Scientific/Engineering :: Artificial Intelligence
Classifier: Topic :: Software Development
Classifier: Topic :: Software Development :: Libraries
Classifier: Topic :: Software Development :: Libraries :: Python Modules
Classifier: Intended Audience :: Developers
Classifier: Intended Audience :: Education
Classifier: Intended Audience :: Science/Research
Classifier: License :: OSI Approved :: MIT License
Classifier: Operating System :: OS Independent
Requires-Python: >=3.10.0
License-File: LICENSE.txt
Requires-Dist: matplotlib>=3.7.1
Requires-Dist: numpy>=1.23.5
Requires-Dist: setuptools>=61.0
Requires-Dist: torch>=2.0.0
Requires-Dist: torchvision>=0.15.1
Requires-Dist: tqdm>=4.65.0
Requires-Dist: scikit-learn>=0.20.0
Requires-Dist: wilds>=2.0.0
Requires-Dist: transformers>=3.5.0
Requires-Dist: umap-learn>=0.5.5
Requires-Dist: grad-cam>=1.5.0
Provides-Extra: dev
Requires-Dist: black>=23.1.0; extra == "dev"
Requires-Dist: flake8>=3.9.2; extra == "dev"
Requires-Dist: pytest>=7.2.1; extra == "dev"
Requires-Dist: properscoring; extra == "dev"
Requires-Dist: build; extra == "dev"
Requires-Dist: twine; extra == "dev"
Provides-Extra: docs
Requires-Dist: ipython>=7.34.0; extra == "docs"
Requires-Dist: nbsphinx>=0.8.12; extra == "docs"
Requires-Dist: sphinx>=5.3.0; extra == "docs"
Requires-Dist: sphinx_rtd_theme>=1.1.1; extra == "docs"
